sht20/__init__.py
sht20/sht20.py
sht20-0.1.4.data/scripts/run-sht20
sht20-0.1.4.dist-info/LICENSE
sht20-0.1.4.dist-info/METADATA
sht20-0.1.4.dist-info/WHEEL
sht20-0.1.4.dist-info/top_level.txt
sht20-0.1.4.dist-info/RECORD
