Metadata-Version: 2.1
Name: sht20
Version: 0.1.4
Summary: Python3 I2C Driver & Application for SHT20 Temperature & Humidity Sensor
Home-page: https://github.com/feyzikesim/sht20
Author: Feyzi Kesim
Author-email: feyzikesim@gmail.com
License: UNKNOWN
Platform: UNKNOWN
Classifier: Programming Language :: Python :: 3
Classifier: License :: OSI Approved :: MIT License
Classifier: Operating System :: OS Independent
Requires-Python: >=3.6
